pysqlitefs/Readme.md
pysqlitefs/__init__.py
pysqlitefs/pysqlitefs.cp313-win_amd64.pyd
pysqlitefs/pysqlitefs.pyi
pysqlitefs/test/test.py
pysqlitefs-1.6.0.dist-info/METADATA
pysqlitefs-1.6.0.dist-info/WHEEL
pysqlitefs-1.6.0.dist-info/top_level.txt
pysqlitefs-1.6.0.dist-info/RECORD
