Metadata-Version: 2.4
Name: pysqlitefs
Version: 1.6.0
Summary: Python bindings for SQLiteFS - Simulate a local filesystem inside a SQLite database
Author: P34ch
License-Expression: MIT
Project-URL: Homepage, https://gitlab.com/p34ch-main/sqlitefs
Project-URL: Bug Reports, https://gitlab.com/p34ch-main/sqlitefs/-/issues
Project-URL: Source, https://gitlab.com/p34ch-main/sqlitefs
Project-URL: Documentation, https://gitlab.com/p34ch-main/sqlitefs/-/blob/main/README.md
Keywords: sqlite,filesystem,database,file,storage,compression,encryption
Classifier: Development Status :: 4 - Beta
Classifier: Intended Audience :: Developers
Classifier: Programming Language :: Python :: 3
Classifier: Programming Language :: Python :: 3.10
Classifier: Programming Language :: Python :: 3.11
Classifier: Programming Language :: Python :: 3.12
Classifier: Programming Language :: Python :: 3.13
Classifier: Programming Language :: Python :: 3.14
Classifier: Programming Language :: C++
Classifier: Topic :: Database
Classifier: Topic :: Software Development :: Libraries :: Python Modules
Classifier: Topic :: System :: Filesystems
Classifier: Operating System :: Microsoft :: Windows
Classifier: Operating System :: POSIX :: Linux
Requires-Python: >=3.9
